multiprocessing_mq/__init__.py
multiprocessing_mq/interactivity.py
multiprocessing_mq/super_queue.py
multiprocessing_mq-0.5.dist-info/LICENSE
multiprocessing_mq-0.5.dist-info/METADATA
multiprocessing_mq-0.5.dist-info/WHEEL
multiprocessing_mq-0.5.dist-info/RECORD
