Metadata-Version: 2.1
Name: multiprocessing_mq
Version: 0.5
Summary: 在多进程内维护一个消息队列，更方便的使用多进程 
Home-page: https://github.com/ovo-Tim/multiprocessing-mq
Author: ovo-tim
Author-email: ovo-tim@qq.com
Classifier: Programming Language :: Python :: 3
Classifier: License :: OSI Approved :: GNU General Public License v3 or later (GPLv3+)
Classifier: Operating System :: OS Independent
License-File: LICENSE
